{"time": 574, "memory": 16200, "problem": {"pid": "B3673", "title": "[语言月赛202210] 垃圾分类", "difficulty": 1, "type": "B"}, "sourceCodeLength": 521, "submitTime": 1778162691, "language": 28, "user": {"uid": 1612738, "name": "Johnny0917", "avatar": "https://cdn.luogu.com.cn/upload/usericon/1612738.png", "slogan": "w(ﾟДﾟ)w做题气的嗷嗷叫", "isAdmin": false, "isBanned": false, "color": "Blue", "ccfLevel": 0, "xcpcLevel": 0, "background": ""}, "id": 277043935, "status": 12, "enableO2": true, "score": 100, "detail": {"compileResult": {"success": true, "opt2": false}, "judgeResult": {"finishedCaseCount": 10, "status": 0, "time": 0, "memory": 0, "score": 0}, "version": 400}, "sourceCode": "#include<bits/stdc++.h>\nusing namespace std;\nint n,c;\nint a[1000001],b[1000001];\nlong long cost[1000001];\nint main()\n{\n    scanf(\"%d%d\",&n,&c);\n    for(int i=1;i<=n;i++)\n    {\n        scanf(\"%d\",&a[i]);\n    }\n    for(int i=1;i<=n;i++)\n    {\n        scanf(\"%d\",&b[i]);\n    }\n    for(int i=1;i<=n;i++)\n    {\n    \tif(b[i]>a[i])\n    \t{\n    \t\tcost[i]=b[i]-a[i];\n\t\t}\n\t\telse\n\t\t{\n\t\t\tcost[i]=0;\n\t\t}\n    }\n    long long ans=0;\n    for(int i=1;i<=n;i++)\n    {\n        ans=ans+cost[i]*c;\n    }\n    printf(\"%lld\",ans);\n    return 0;\n}", "_detail_requested": true, "_cached_at": "2026-06-05 12:20:03"}