{"time": 31, "memory": 680, "problem": {"pid": "B3838", "title": "[GESP202306 一级] 时间规划", "difficulty": 1, "type": "B"}, "sourceCodeLength": 227, "submitTime": 1751448737, "language": 28, "user": {"uid": 1612738, "name": "Johnny0917", "avatar": "https://cdn.luogu.com.cn/upload/usericon/1612738.png", "slogan": "w(ﾟДﾟ)w做题气的嗷嗷叫", "isAdmin": false, "isBanned": false, "color": "Blue", "ccfLevel": 0, "xcpcLevel": 0, "background": ""}, "id": 222084460, "status": 12, "enableO2": true, "score": 100, "detail": {"compileResult": {"success": true, "opt2": false}, "judgeResult": {"finishedCaseCount": 10, "status": 0, "time": 0, "memory": 0, "score": 0}, "version": 400}, "sourceCode": "#include<cstdio>\nusing namespace std;\n\nint main()\n{\n\tint h[3],m[3],cha=0;\n\tscanf(\"%d%d%d%d\",&h[1],&m[1],&h[2],&m[2]);\n\tif(h[2]<h[1])\n\t{\n\t\th[2]+=23;\n\t}\n\tcha=cha+(h[2]-h[1])*60;\n\tcha=cha+m[2]-m[1];\n\tprintf(\"%d\",cha);\n\treturn 0;\n}", "_detail_requested": true, "_cached_at": "2026-06-05 12:19:50"}