{"time": 21, "memory": 680, "problem": {"pid": "P1855", "title": "榨取kkksc03", "difficulty": 2, "type": "P"}, "sourceCodeLength": 415, "submitTime": 1737338783, "language": 27, "user": {"uid": 1353311, "name": "AC_Coder4869", "avatar": "https://cdn.luogu.com.cn/upload/usericon/1353311.png", "slogan": "願", "isAdmin": false, "isBanned": false, "color": "Green", "ccfLevel": 6, "xcpcLevel": 0, "background": ""}, "id": 199370943, "status": 12, "enableO2": true, "score": 100, "detail": {"compileResult": {"success": true, "opt2": false}, "judgeResult": {"finishedCaseCount": 5, "status": 0, "time": 0, "memory": 0, "score": 0}, "version": 400}, "sourceCode": "#include<cstdio>\r\n#include<iostream>\r\n#include<algorithm>\r\nusing namespace std;\r\n\r\nint dp[205][205], m[205], t[205];\r\n\r\nint main(){\r\n\tint n, M, T;\r\n\tcin >> n >> M >> T;\r\n\tfor(int i = 1; i <= n; i++)\r\n\t\tcin >> m[i] >> t[i];\r\n\tfor(int i = 1; i <= n; i++)\r\n\t\tfor(int j = M; j >= m[i]; j--)\r\n\t\t\tfor(int k = T; k >= t[i]; k--)\r\n\t\t\t\tdp[j][k] = max(dp[j][k], dp[j - m[i]][k - t[i]] + 1);\r\n\tcout << dp[M][T];\r\n\treturn 0;\r\n}", "_detail_requested": true, "_cached_at": "2026-06-05 16:07:28"}