{"time": 240, "memory": 1092, "problem": {"pid": "P10250", "title": "[GESP样题 六级] 下楼梯", "difficulty": 2, "type": "P"}, "sourceCodeLength": 232, "submitTime": 1755263159, "language": 28, "user": {"uid": 1669626, "name": "afei2208", "avatar": "https://cdn.luogu.com.cn/upload/usericon/1669626.png", "slogan": "", "isAdmin": false, "isBanned": false, "color": "Green", "ccfLevel": 0, "xcpcLevel": 0, "background": ""}, "id": 231207533, "status": 12, "enableO2": true, "score": 100, "detail": {"compileResult": {"success": true, "opt2": false}, "judgeResult": {"finishedCaseCount": 60, "status": 0, "time": 0, "memory": 0, "score": 0}, "version": 400}, "sourceCode": "#include<iostream>\nusing namespace std;\nint n;\nint main() {\n    cin >> n;\n    long long a[n];\n    a[0]=1;\n    a[1]=2;\n    a[2]=4;\n    for(int i=3;i<n;i++){\n        a[i]=(a[i-1]+a[i-2]+a[i-3]);\n    }\n    cout<<a[n-1];\n    return 0;\n}", "_detail_requested": true, "_cached_at": "2026-06-05 16:49:06"}