{"time": 77, "memory": 3324, "problem": {"pid": "P1332", "title": "血色先锋队", "difficulty": 3, "type": "P"}, "sourceCodeLength": 1058, "submitTime": 1759825588, "language": 28, "user": {"uid": 1368240, "name": "littlefoxlxl", "avatar": "https://cdn.luogu.com.cn/upload/usericon/1368240.png", "slogan": "", "isAdmin": false, "isBanned": false, "color": "Green", "ccfLevel": 0, "xcpcLevel": 0, "background": ""}, "id": 239217248, "status": 14, "enableO2": true, "score": 0, "detail": {"compileResult": {"success": true, "opt2": false}, "judgeResult": {"finishedCaseCount": 10, "status": 0, "time": 0, "memory": 0, "score": 0}, "version": 400}, "sourceCode": "#include<bits/stdc++.h>\nusing namespace std;\nint n,m,t[100005],b[1125005],vis[1505][1505],k,tot,mmax,tmp;\nchar a[1505][1505];\nint dx[]={0,-1,-1,-1,0,0,1,1,1};\nint dy[]={0,-1,0,1,-1,1,-1,0,1};\nvoid printf()\n{\n\tfor(int i=1;i<=n;i++)\n\t{\n\t\tfor(int j=1;j<=m;j++)\n\t\t{\n\t\t\tcout<<vis[i][j]<<\" \";\n\t\t}\n\t\tcout<<\"\\n\";\n\t}\n\tcout<<\"\\n\";\n}\nvoid dfs(int x,int y)\n{\n\tfor(int i=1;i<=8;i++)\n\t{\n\t\tint nx=x+dx[i];\n\t\tint ny=y+dy[i];\n\t\tif(nx>=1 and ny>=1 and nx<=n and ny<=m and a[nx][ny]=='*' and vis[nx][ny]==0)\n\t\t{\n\t\t\tvis[nx][ny]=1;\n\t\t\ttot++;\n\t\t\tdfs(nx,ny);\n\t\t}\n\t}\n}\nint main()\n{\n\tcin>>n>>m;\n\tfor(int i=1;i<=n;i++)\n\t{\n\t\tfor(int j=1;j<=m;j++)\n\t\t{\n\t\t\tcin>>a[i][j];\n\t\t}\n\t}\n\tfor(int i=1;i<=n;i++)\n\t{\n\t\tfor(int j=1;j<=m;j++)\n\t\t{\n\t\t\tif(a[i][j]=='*' and vis[i][j]==0)\n\t\t\t{\n\t\t\t\tk++;\n\t\t\t\ttot=1;\n\t\t\t\tvis[i][j]=1;\n\t\t\t\tdfs(i,j);\n\t\t\t\tt[tot]++;\n\t\t\t\ttmp=max(tmp,tot);\n//\t\t\t\tprintf();\n\t\t\t}\n\t\t}\n\t}\n\tk=0;\n\tfor(int i=1;i<=1005;i++)\n\t{\n\t\tif(t[i]!=0)\n\t\t{\n//\t\t\tcout<<t[i]<<\" \";\n\t\t\tk++;\n//\t\t\ttot++;\n\t\t\tb[k]=t[i]*i;\n\t\t\tmmax=max(b[k],mmax);\n//\t\t\tmmax=mmax(i,mmax);\n\t\t}\n\t}\n\tcout<<k<<\" \"<<mmax;\n\treturn 0;\n}", "_detail_requested": true, "_cached_at": "2026-06-05 10:40:41"}