{"time": 2035, "memory": 816, "problem": {"pid": "P14074", "title": "[GESP202509 五级] 有趣的数字和", "difficulty": 3, "type": "P"}, "sourceCodeLength": 231, "submitTime": 1779360656, "language": 28, "user": {"uid": 1368240, "name": "littlefoxlxl", "avatar": "https://cdn.luogu.com.cn/upload/usericon/1368240.png", "slogan": "", "isAdmin": false, "isBanned": false, "color": "Green", "ccfLevel": 0, "xcpcLevel": 0, "background": ""}, "id": 278754988, "status": 14, "enableO2": true, "score": 40, "detail": {"compileResult": {"success": true, "opt2": false}, "judgeResult": {"finishedCaseCount": 11, "status": 0, "time": 0, "memory": 0, "score": 0}, "version": 400}, "sourceCode": "#include<bits/stdc++.h>\nusing namespace std;\nlong long l,r,ans;\nint main()\n{\n\tcin>>l>>r;\n\tfor(int i=l;i<=r;i++)\n\t{\n\t\tif(i%12==1 or i%12==2 or i%12==4 or i%12==7 or i%12==8 or i%12==11)\n\t\t{\n\t\t\tans+=i;\n\t\t}\n\t}\n\tcout<<ans;\n\treturn 0;\n}", "_detail_requested": true, "_cached_at": "2026-06-05 10:40:37"}