{"time": 868, "memory": 83988, "problem": {"pid": "P1533", "title": "可怜的狗狗", "difficulty": 5, "type": "P"}, "sourceCodeLength": 1776, "submitTime": 1768381972, "language": 12, "user": {"uid": 814130, "name": "Moya_Rao", "avatar": "https://cdn.luogu.com.cn/upload/usericon/814130.png", "slogan": "＆Yore_Snow | | 退犇，关私信，等我不颓了再考虑复活，对不起。", "badge": "啾？啾！", "isAdmin": false, "isBanned": false, "color": "Red", "ccfLevel": 6, "xcpcLevel": 0, "background": "https://cdn.luogu.com.cn/upload/image_hosting/m8n299ax.png"}, "id": 257545548, "status": 12, "enableO2": true, "score": 100, "detail": {"compileResult": {"success": true, "opt2": false}, "judgeResult": {"finishedCaseCount": 10, "status": 0, "time": 0, "memory": 0, "score": 0}, "version": 400}, "sourceCode": "#include<bits/stdc++.h>\n#define LL long long\n#define UInt unsigned int\n#define ULL unsigned long long\n#define LD long double\n#define pii pair<int,int>\n#define pLL pair<LL,LL>\n#define pDD pair<LD,LD>\n#define fr first\n#define se second\n#define pb push_back\n#define isr insert\nusing namespace std;\nconst int N = 3e5+5;\nconst int K = (N<<5);\nint n,m,Q,p[N],a[N];\nint node_cnt,Rt[N],ls[K],rs[K],sum[K];\nint read(){\n    int su=0,pp=1;char ch=getchar();\n    while(ch<'0'||ch>'9'){if(ch=='-')pp=-1;ch=getchar();}\n    while(ch>='0'&&ch<='9'){su=su*10+ch-'0';ch=getchar();}\n    return su*pp;\n}\nvoid build(int &u,int l,int r){\n    u=(++node_cnt);//动态开点\n    if(l==r)return;//叶子\n    int mid=(l+r)>>1;//取中间值切半\n    build(ls[u],l,mid);//左儿子\n    build(rs[u],mid+1,r);//右儿子\n    return;//处理完毕\n}\nint update(int u,int l,int r,int k){\n    int v=(++node_cnt);//开新点\n    ls[v]=ls[u],rs[v]=rs[u];sum[v]=sum[u]+1;//更新值\n    if(l==r)return v;//叶子\n    int mid=(l+r)>>1;//取中间值切半\n    if(k<=mid)ls[v]=update(ls[v],l,mid,k);//左儿子\n    else rs[v]=update(rs[v],mid+1,r,k);//右儿子\n    return v;//处理完毕\n}\nint query(int u,int v,int l,int r,int k){\n    int mid=((l+r)>>1);//取中间值切半\n    int x=sum[ls[v]]-sum[ls[u]];//方向判断\n    if(l==r)return l;//叶子\n    if(x>=k)return query(ls[u],ls[v],l,mid,k);//往左跑\n    else return query(rs[u],rs[v],mid+1,r,k-x);//往右跑\n}\nint main(){\n    n=read(),Q=read();//读入\n    for(int i=1;i<=n;i++)p[i]=read(),a[i]=p[i];//读入\n    sort(a+1,a+n+1);//排序\n    m=unique(a+1,a+n+1)-a-1;//去重\n    build(Rt[0],1,m);//建树\n    for(int i=1;i<=n;i++){\n        int tmp=lower_bound(a+1,a+m+1,p[i])-a;\n        Rt[i]=update(Rt[i-1],1,m,tmp);\n    }//预处理点修改\n    while(Q--){//处理查询\n        int l=read(),r=read(),k=read();//读入\n        int id=query(Rt[l-1],Rt[r],1,m,k);//查询\n        cout<<a[id]<<\"\\n\";//输出\n    }\n    return 0;\n}", "_detail_requested": true, "_cached_at": "2026-06-05 11:21:50"}