{"time": 31, "memory": 564, "problem": {"pid": "P1048", "title": "[NOIP 2005 普及组] 采药", "difficulty": 2, "type": "P"}, "sourceCodeLength": 280, "submitTime": 1750313401, "language": 28, "user": {"uid": 688054, "name": "markwang0529", "avatar": "https://cdn.luogu.com.cn/upload/usericon/688054.png", "slogan": "无限进步", "isAdmin": false, "isBanned": false, "color": "Orange", "ccfLevel": 5, "xcpcLevel": 0, "background": ""}, "id": 220862243, "status": 12, "enableO2": true, "score": 100, "detail": {"compileResult": {"success": true, "opt2": false}, "judgeResult": {"finishedCaseCount": 10, "status": 0, "time": 0, "memory": 0, "score": 0}, "version": 400}, "sourceCode": "#include<bits/stdc++.h>\nusing namespace std;\nlong long dp[10000005],t,m,a[10005],b[10005];\nint main()\n{\n\tcin>>t>>m;\n\tfor(int i=1;i<=m;i++)\n\t{\n\t\tcin>>a[i]>>b[i];\n\t}\n\tfor(int i=1;i<=m;i++)\n\t{\n\t\tfor(int j=t;j>=a[i];j--) dp[j]=max(dp[j],b[i]+dp[j-a[i]]);\n\t}\n\tcout<<dp[t];\n\treturn 0;\n}", "_detail_requested": true, "_cached_at": "2026-06-05 17:34:06"}