{"time": 248, "memory": 14016, "problem": {"pid": "P10723", "title": "[GESP202406 七级] 黑白翻转", "difficulty": 4, "type": "P"}, "sourceCodeLength": 685, "submitTime": 1741088095, "language": 11, "user": {"uid": 688054, "name": "markwang0529", "avatar": "https://cdn.luogu.com.cn/upload/usericon/688054.png", "slogan": "无限进步", "isAdmin": false, "isBanned": false, "color": "Orange", "ccfLevel": 5, "xcpcLevel": 0, "background": ""}, "id": 205945791, "status": 12, "enableO2": true, "score": 100, "detail": {"compileResult": {"success": true, "opt2": false}, "judgeResult": {"finishedCaseCount": 45, "status": 0, "time": 0, "memory": 0, "score": 0}, "version": 400}, "sourceCode": "#include <bits/stdc++.h>\nusing namespace std;\nconst int N=100005;\nint n,vis[N],cnt,root,ans;\nvector<int> g[N];\nvoid dfs(int u,int fa)\n{\n    for(int i=0;i<g[u].size();i++)\n    {\n        int v=g[u][i];\n        if(v==fa) continue;\n        dfs(v,u);\n        vis[u]+=vis[v];\n    }\n}\nint main()\n{\n    cin>>n;\n    for(int i=1;i<=n;i++)\n    {\n        cin>>vis[i];\n        if(vis[i])\n        {\n            cnt++;\n            root=i;\n        }\n    }\n    for(int i=1;i<n;i++)\n    {\n        int x,y;\n        cin>>x>>y;\n        g[x].push_back(y);\n        g[y].push_back(x);\n    }\n    dfs(root,0);\n    for(int i=1;i<=n;i++)\n    {\n        ans+=bool(vis[i]);\n    }\n    cout<<(ans-cnt);\n    return 0;\n}", "_detail_requested": true, "_cached_at": "2026-06-05 17:19:43"}