{"time": 153, "memory": 9108, "problem": {"pid": "P2097", "title": "资料分发 1", "difficulty": 2, "type": "P"}, "sourceCodeLength": 483, "submitTime": 1751798501, "language": 28, "user": {"uid": 688054, "name": "markwang0529", "avatar": "https://cdn.luogu.com.cn/upload/usericon/688054.png", "slogan": "无限进步", "isAdmin": false, "isBanned": false, "color": "Orange", "ccfLevel": 5, "xcpcLevel": 0, "background": ""}, "id": 222633588, "status": 12, "enableO2": true, "score": 100, "detail": {"compileResult": {"success": true, "opt2": false}, "judgeResult": {"finishedCaseCount": 10, "status": 0, "time": 0, "memory": 0, "score": 0}, "version": 400}, "sourceCode": "#include <bits/stdc++.h>\nusing namespace std;\nconst int N=100005;\nint n,m,vis[N],ans;\nvector<int> g[N];\nvoid dfs(int x)\n{\n\tvis[x]=1;\n\tfor(int i=0;i<g[x].size();i++)\n\t{\n\t\tint v=g[x][i];\n\t\tif(vis[v]==0) dfs(v);\n\t}\n}\nint main()\n{\n\tios::sync_with_stdio(0);\n\tcin.tie(0),cout.tie(0);\n\tcin>>n>>m;\n\tfor(int i=1;i<=m;i++)\n\t{\n\t\tint x,y;\n\t\tcin>>x>>y;\n\t\tg[x].push_back(y);\n\t\tg[y].push_back(x);\n\t}\n\tfor(int i=1;i<=n;i++)\n\t{\n\t\tif(vis[i]==0)\n\t\t{\n\t\t\tans++;\n\t\t\tdfs(i);\n\t\t}\n\t}\n\tcout<<ans;\n\treturn 0;\n}", "_detail_requested": true, "_cached_at": "2026-06-05 17:30:26"}