{"time": 523, "memory": 2352, "problem": {"pid": "P2619", "title": "[国家集训队] Tree I", "difficulty": 5, "type": "P"}, "sourceCodeLength": 1164, "submitTime": 1778312234, "language": 11, "user": {"uid": 688054, "name": "markwang0529", "avatar": "https://cdn.luogu.com.cn/upload/usericon/688054.png", "slogan": "无限进步", "isAdmin": false, "isBanned": false, "color": "Orange", "ccfLevel": 5, "xcpcLevel": 0, "background": ""}, "id": 277180821, "status": 12, "enableO2": true, "score": 100, "detail": {"compileResult": {"success": true, "opt2": false}, "judgeResult": {"finishedCaseCount": 20, "status": 0, "time": 0, "memory": 0, "score": 0}, "version": 400}, "sourceCode": "#include <bits/stdc++.h>\nusing namespace std;\n#define dbg(x) cerr<<#x\" = \"<<(x)<<endl;\n#define ll long long\nconst int N=100005;\nint fa[N],n,m,need;\nstruct node\n{\n\tint s,t,v,c;\n\tbool operator<(const node other)\n\t{\n\t\tif(v==other.v) return c<other.c;\n\t\telse return v<other.v;\n\t}\n} g[N];\nint find(int x)\n{\n\tif(fa[x]==x) return x;\n\treturn fa[x]=find(fa[x]);\n}\nint sum,ans,cntwhite,cnt;\nvoid kruskal()\n{\n\tsort(g+1,g+1+m);\n\tfor(int i=1;cnt<n-1;i++)\n\t{\n\t\tint fs=find(g[i].s),ft=find(g[i].t);\n\t\tif(fs==ft) continue;\n\t\tcnt++;\n\t\tfa[fs]=ft;\n\t\tif(g[i].c==0) cntwhite++;\n\t\tsum+=g[i].v;\n\t}\n}\nint main()\n{\n\tios::sync_with_stdio(0);\n\tcin.tie(0),cout.tie(0);\n//\tfreopen(\".in\",\"r\",stdin);\n//\tfreopen(\".out\",\"w\",stdout);\n\tcin>>n>>m>>need;\n\tfor(int i=1;i<=m;i++)\n\t{\n\t\tcin>>g[i].s>>g[i].t>>g[i].v>>g[i].c;\n\t\tg[i].s++,g[i].t++;\n\t}\n\tint l=-100,r=100;\n\twhile(l<=r)\n\t{\n\t\tint mid=(l+r)/2;\n\t\tfor(int i=1;i<=m;i++)\n\t\t{\n\t\t\tif(g[i].c==0) g[i].v+=mid;\n\t\t}\n\t\tfor(int i=1;i<=n;i++) fa[i]=i;\n\t\tsum=0,cnt=0,cntwhite=0;\n\t\tkruskal();\n\t\tif(cntwhite>=need)\n\t\t{\n\t\t\tl=mid+1;\n\t\t\tans=sum-need*mid;\n\t\t}\n\t\telse r=mid-1;\n\t\tfor(int i=1;i<=m;i++)\n\t\t{\n\t\t\tif(g[i].c==0) g[i].v-=mid;\n\t\t}\n\t}\n\tcout<<ans;\n\treturn 0;\n}\n", "_detail_requested": true, "_cached_at": "2026-06-05 17:05:48"}