{"time": 4441, "memory": 60336, "problem": {"pid": "P4284", "title": "[SHOI2014] 概率充电器", "difficulty": 5, "type": "P"}, "sourceCodeLength": 1047, "submitTime": 1772159403, "language": 11, "user": {"uid": 688054, "name": "markwang0529", "avatar": "https://cdn.luogu.com.cn/upload/usericon/688054.png", "slogan": "无限进步", "isAdmin": false, "isBanned": false, "color": "Orange", "ccfLevel": 5, "xcpcLevel": 0, "background": ""}, "id": 264327032, "status": 12, "enableO2": true, "score": 100, "detail": {"compileResult": {"success": true, "opt2": false}, "judgeResult": {"finishedCaseCount": 21, "status": 0, "time": 0, "memory": 0, "score": 0}, "version": 400}, "sourceCode": "#include <bits/stdc++.h>\nusing namespace std;\n#define ll long long\nconst int N=500005;\nstruct node\n{\n\tint v;\n    double w;\n};\nvector<node> g[N];\nint n;\ndouble dp[N];\nvoid dfs1(int u,int f)\n{\n\tfor(int i=0;i<g[u].size();i++)\n\t{\n\t\tint v=g[u][i].v;\n\t\tif(f==v) continue;\n\t\tdfs1(v,u);\n\t\tdp[u]+=dp[v]*(1-dp[u])*g[u][i].w;\n\t}\n}\nvoid dfs2(int u,int f)\n{\n\tfor(int i=0;i<g[u].size();i++)\n\t{\n\t\tint v=g[u][i].v;\n\t\tif(v==f) continue;\n\t\tdouble p=(1-dp[v])*(dp[u]-dp[v]*g[u][i].w),q=(1-dp[v]*g[u][i].w);\n\t\tif(q<=1e-8)\n\t\t{\n\t\t\tdfs2(v,u);\n\t\t\tcontinue;\n\t\t}\n\t\tdp[v]+=p/q*g[u][i].w;\n\t\tdfs2(v,u);\n\t}\n}\nint main()\n{\n\tios::sync_with_stdio(0);\n\tcin.tie(0),cout.tie(0);\n//\tfreopen(\".in\",\"r\",stdin);\n//\tfreopen(\".out\",\"w\",stdout);\n\tcin>>n;\n\tfor(int i=1;i<n;i++)\n\t{\n\t\tint u,v;\n\t\tdouble w;\n\t\tcin>>u>>v>>w;\n\t\tg[u].push_back(node{v,w/100});\n\t\tg[v].push_back(node{u,w/100});\n\t}\n\tfor(int i=1;i<=n;i++)\n\t{\n\t\tdouble num;\n\t\tcin>>num;\n\t\tdp[i]=num/100;\n\t}\n\tdfs1(1,0);\n\tdfs2(1,0);\n\tdouble ans=0;\n\tfor(int i=1;i<=n;i++)\n\t{\n\t\tans+=dp[i];\n\t}\n\tcout<<fixed<<setprecision(6)<<ans;\n\treturn 0;\n}", "_detail_requested": true, "_cached_at": "2026-06-05 17:03:22"}