{"time": 61, "memory": 680, "problem": {"pid": "P5015", "title": "[NOIP 2018 普及组] 标题统计", "difficulty": 1, "type": "P"}, "sourceCodeLength": 214, "submitTime": 1728285665, "language": 28, "user": {"uid": 688054, "name": "markwang0529", "avatar": "https://cdn.luogu.com.cn/upload/usericon/688054.png", "slogan": "无限进步", "isAdmin": false, "isBanned": false, "color": "Orange", "ccfLevel": 5, "xcpcLevel": 0, "background": ""}, "id": 180711955, "status": 12, "enableO2": true, "score": 100, "detail": {"compileResult": {"success": true, "opt2": false}, "judgeResult": {"finishedCaseCount": 20, "status": 0, "time": 0, "memory": 0, "score": 0}, "version": 400}, "sourceCode": "#include<bits/stdc++.h>\nusing namespace std;\nstring s;\nint ans=0;\nint main()\n{\n    getline(cin,s);\n    for(int i=0;i<s.size();i++)\n    {\n        if(s[i]!=' '&&s[i]!='\\n') ans++;\n    }\n    cout<<ans;\n    return 0;\n}", "_detail_requested": true, "_cached_at": "2026-06-05 17:36:38"}