{"time": 100, "memory": 1064, "problem": {"pid": "B4377", "title": "[蓝桥杯青少年组省赛 2025] 平衡奇偶位置的字符交换", "difficulty": 2, "type": "B"}, "sourceCodeLength": 478, "submitTime": 1754909415, "language": 34, "user": {"uid": 1351761, "name": "chenhany", "avatar": "https://cdn.luogu.com.cn/upload/usericon/1351761.png", "slogan": "⬅️这是一个五年级的蒟蒻(真的)||AT同名||骗关15日提醒，1月拉黑||支持壶关（私信）✉️||私信✉️不允许wyy和接龙||等几周就橙了，不要取关", "isAdmin": false, "isBanned": false, "color": "Green", "ccfLevel": 0, "xcpcLevel": 0, "background": "https://cdn.luogu.com.cn/upload/image_hosting/qavz1wyv.png"}, "id": 230275422, "status": 12, "enableO2": true, "score": 100, "detail": {"compileResult": {"success": true, "opt2": false}, "judgeResult": {"finishedCaseCount": 20, "status": 0, "time": 0, "memory": 0, "score": 0}, "version": 400}, "sourceCode": "#include<bits/stdc++.h>  //万能头文件\nusing namespace std;\nint x, y;\nstring a;    //定义变量\nint main() {\n\tcin >> a; //输入字符串\n\ta=\" \"+a;  //这样输入的第一个字符就在下标1上了\n\tfor (int i = 1; i < a.size(); i++) {\n\t\tif (a[i] == 'A') {\n\t\t\tif (i % 2 == 1) {\n\t\t\t\tx++;  //统计字符串的奇数下标上$A$的数量\n\t\t\t} else {\n\t\t\t\ty++;   //统计字符串的偶数下标上$A$的数量\n\t\t\t}\n\n\t\t}\n\t}\n\tif ((x + y) % 2 == 1) { //判断A的数量是不是2的倍数\n\t\tcout << \"-1\";\n\t\treturn 0;\n\t}\n\tif(x>y) cout << (x - y) / 2; //输出结果\n    else cout << (y - x) / 2;  //输出结果\n\treturn 0;  //结束\n}", "_detail_requested": true, "_cached_at": "2026-06-05 17:30:42"}