{"time": 997, "memory": 11708, "problem": {"pid": "P10113", "title": "[GESP202312 八级] 大量的工作沟通", "difficulty": 3, "type": "P"}, "sourceCodeLength": 1291, "submitTime": 1773300755, "language": 11, "user": {"uid": 1351761, "name": "chenhany", "avatar": "https://cdn.luogu.com.cn/upload/usericon/1351761.png", "slogan": "⬅️这是一个五年级的蒟蒻(真的)||AT同名||骗关15日提醒，1月拉黑||支持壶关（私信）✉️||私信✉️不允许wyy和接龙||等几周就橙了，不要取关", "isAdmin": false, "isBanned": false, "color": "Green", "ccfLevel": 0, "xcpcLevel": 0, "background": "https://cdn.luogu.com.cn/upload/image_hosting/qavz1wyv.png"}, "id": 266696414, "status": 12, "enableO2": true, "score": 100, "detail": {"compileResult": {"success": true, "opt2": false}, "judgeResult": {"finishedCaseCount": 21, "status": 0, "time": 0, "memory": 0, "score": 0}, "version": 400}, "sourceCode": "#include<bits/stdc++.h>\nusing namespace std;\nint a[100005];\nint f[100005][25];\nint d[100005],n,q;\nint dfs(int x){\n    if(a[x]!=0) return a[x];\n    if(x==0){\n        return a[x]=0;\n    }else{\n        \n        return a[x]=max(x,dfs(f[x][0]));\n    }\n}\nint dfs2(int x){\n    if(d[x]!=0) return d[x];\n    if(x==0){\n        return d[x]=0;\n    }else{\n        \n        return d[x]=dfs2(f[x][0])+1;\n    }\n}\nint lca(int x,int y){\n    if(d[x] < d[y]) swap(x, y);\n    int z = d[x] - d[y];\n    for(int i=0; i<=20; i++) {\n        if(z >> i & 1) x = f[x][i];\n    }\n    if(x == y) return x;\n   for(int i=20; i>=0; i--) {\n        if(f[x][i] != f[y][i]) {\n            x = f[x][i];\n            y = f[y][i];\n        }\n    }\n    return f[x][0];\n}\nint main(){\n    cin>>n;\n    f[0][0]=0;\n    d[0]=0;\n    for(int i=1;i<n;i++){\n        cin>>f[i][0];\n    }\n     for(int i=1;i<n;i++){\n        d[i]=dfs2(i);\n    }\n    for(int i=1;i<n;i++){\n        a[i]=dfs(i);\n    }\n    \n    for(int i=1;i<=20;i++){\n        for(int j=0;j<n;j++){\n            f[j][i]=f[f[j][i-1]][i-1];\n        }\n    }\n    cin>>q;\n    for(int i=1;i<=q;i++){\n        int m;\n        cin>>m;\n        int x,y;\n        cin>>x;\n        for(int j=2;j<=m;j++){\n            cin>>y;\n            x=lca(x,y);\n        }\n        cout<<a[x]<<\"\\n\";\n    }\n    return 0;\n}", "_detail_requested": true, "_cached_at": "2026-06-05 17:12:45"}