{"time": 754, "memory": 35344, "problem": {"pid": "P1197", "title": "[JSOI2008] 星球大战", "difficulty": 4, "type": "P"}, "sourceCodeLength": 1269, "submitTime": 1754552426, "language": 27, "user": {"uid": 768551, "name": "lfh2024", "avatar": "https://cdn.luogu.com.cn/upload/usericon/768551.png", "slogan": "这个家伙很勤快，什么都留下了...", "isAdmin": false, "isBanned": false, "color": "Red", "ccfLevel": 7, "xcpcLevel": 0, "background": "https://cdn.luogu.com.cn/upload/image_hosting/dqbnruu6.png"}, "id": 229415117, "status": 12, "enableO2": true, "score": 100, "detail": {"compileResult": {"success": true, "opt2": false}, "judgeResult": {"finishedCaseCount": 10, "status": 0, "time": 0, "memory": 0, "score": 0}, "version": 400}, "sourceCode": "#include<bits/stdc++.h>\nusing namespace std;\nint x[2000010],fa[2000010],y[2000010],a[2000010],flag[2000010];\nvector<int> mp[2000010];\nint find(int x)\n{\n    return(x==fa[x]?x:fa[x]=find(fa[x]));\n}\nint cnt;\nvoid merge(int x,int y)\n{\n    int a=find(x),b=find(y);\n    if(a!=b)\n    {\n        cnt--;\n        fa[a]=b;\n    }\n}\nint main()\n{\n    int n,m;\n    scanf(\"%d%d\",&n,&m);\n    for(int i=1;i<=n;i++)\n    {\n        fa[i]=i;\n    }\n    cnt=0;\n    for(int i=1;i<=m;i++)\n    {\n        scanf(\"%d%d\",&x[i],&y[i]);\n        x[i]++;\n        y[i]++;\n        mp[x[i]].push_back(y[i]);\n        mp[y[i]].push_back(x[i]);\n    }\n    int k;\n    scanf(\"%d\",&k);\n    for(int i=1;i<=k;i++)\n    {\n        scanf(\"%d\",&a[i]);\n        a[i]++;\n        flag[a[i]]=1;\n    }\n    cnt=n-k;\n    for(int i=1;i<=m;i++)\n    {\n        if(!flag[x[i]]&&!flag[y[i]])\n        {\n            merge(x[i],y[i]);\n        }\n    }\n    vector<int> ans;\n    ans.push_back(cnt);\n    for(int i=k;i>=1;i--)\n    {\n        flag[a[i]]=0;\n        cnt++;\n        for(int j:mp[a[i]])\n        {\n            if(!flag[j])\n            {\n                merge(a[i],j);\n            }\n        }\n        ans.push_back(cnt);\n    }\n    reverse(ans.begin(),ans.end());\n    for(int i:ans)\n    {\n        printf(\"%d\\n\",i);\n    }\n    return 0;\n}", "_detail_requested": true, "_cached_at": "2026-06-05 18:20:47"}