{"time": 305, "memory": 9320, "problem": {"pid": "P1231", "title": "教辅的组成", "difficulty": 6, "type": "P"}, "sourceCodeLength": 2257, "submitTime": 1774691372, "language": 27, "user": {"uid": 768551, "name": "lfh2024", "avatar": "https://cdn.luogu.com.cn/upload/usericon/768551.png", "slogan": "这个家伙很勤快，什么都留下了...", "isAdmin": false, "isBanned": false, "color": "Red", "ccfLevel": 7, "xcpcLevel": 0, "background": "https://cdn.luogu.com.cn/upload/image_hosting/dqbnruu6.png"}, "id": 270376505, "status": 12, "enableO2": true, "score": 100, "detail": {"compileResult": {"success": true, "opt2": false}, "judgeResult": {"finishedCaseCount": 10, "status": 0, "time": 0, "memory": 0, "score": 0}, "version": 400}, "sourceCode": "#include<bits/stdc++.h>\nusing namespace std;\nconst long long N=200010,M=1000010;\nlong long head[N],now[N],tot=1,d[N],n,m,s,t;\nbool vis[N];\nstruct edge\n{\n    long long to,flow,nxt;\n}e[M];\nvoid add1(long long u,long long v,long long w)\n{\n    e[++tot]={v,w,head[u]};\n    head[u]=tot;\n}\nvoid add(long long u,long long v,long long w)\n{\n    add1(u,v,w);\n    add1(v,u,0);\n}\nbool bfs()\n{\n    memset(d,0,sizeof(d));\n    d[s]=1;\n    queue<long long> q;\n    q.push(s);\n    while(!q.empty())\n    {\n        long long t=q.front();\n        q.pop();\n        for(long long i=head[t];i;i=e[i].nxt)\n        {\n            long long v=e[i].to,val=e[i].flow;\n            if(val&&!d[v])\n            {\n                d[v]=d[t]+1;\n                if(v==::t)\n                {\n                    return true;\n                }\n                q.push(v);\n            }\n        }\n    }\n    return false;\n}\nlong long dfs(long long x,long long flow)\n{\n    if(x==t||flow==0)\n    {\n        return flow;\n    }\n    long long sum=0;\n    for(long long i=now[x];i;i=e[i].nxt)\n    {\n        now[x]=i;\n        long long v=e[i].to;\n        if(d[v]==d[x]+1&&e[i].flow)\n        {\n            long long tmp=dfs(v,min(flow,e[i].flow));\n            e[i].flow-=tmp;\n            e[i^1].flow+=tmp;\n            sum+=tmp;\n            flow-=tmp;\n            if(flow==0)\n            {\n                break;\n            }\n        }\n    }\n    if(sum==0)\n    {\n        d[x]=0;\n    }\n    return sum;\n}\nlong long dinic()\n{\n    long long ans=0;\n    while(bfs())\n    {\n        memcpy(now,head,sizeof(head));\n        ans+=dfs(s,2e9);\n    }\n    return ans;\n}\nint main()\n{\n    long long p,q;\n    scanf(\"%lld%lld%lld\",&n,&p,&q);\n    s=n*2+p+q+1;\n    t=s+1;\n    long long m;\n    scanf(\"%lld\",&m);\n    for(long long i=1;i<=m;i++)\n    {\n        long long x,y;\n        scanf(\"%lld%lld\",&x,&y);\n        add(y,x+p+q,1);\n    }\n    scanf(\"%lld\",&m);\n    for(long long i=1;i<=m;i++)\n    {\n        long long x,y;\n        scanf(\"%lld%lld\",&x,&y);\n        add(x+p+q+n,y+p,1);\n    }\n    for(long long i=1;i<=n;i++)\n    {\n        add(i+p+q,i+p+q+n,1);\n    }\n    for(long long i=1;i<=p;i++)\n    {\n        add(s,i,1);\n    }\n    for(long long i=1;i<=q;i++)\n    {\n        add(i+p,t,1);\n    }\n    printf(\"%lld\",dinic());\n    return 0;\n}", "_detail_requested": true, "_cached_at": "2026-06-05 16:17:51"}