{"time": 5863, "memory": 118788, "problem": {"pid": "P2839", "title": "[国家集训队] middle", "difficulty": 6, "type": "P"}, "sourceCodeLength": 2794, "submitTime": 1774778187, "language": 27, "user": {"uid": 768551, "name": "lfh2024", "avatar": "https://cdn.luogu.com.cn/upload/usericon/768551.png", "slogan": "这个家伙很勤快，什么都留下了...", "isAdmin": false, "isBanned": false, "color": "Red", "ccfLevel": 7, "xcpcLevel": 0, "background": "https://cdn.luogu.com.cn/upload/image_hosting/dqbnruu6.png"}, "id": 270867829, "status": 12, "enableO2": true, "score": 100, "detail": {"compileResult": {"success": true, "opt2": false}, "judgeResult": {"finishedCaseCount": 21, "status": 0, "time": 0, "memory": 0, "score": 0}, "version": 400}, "sourceCode": "#include<bits/stdc++.h>\nusing namespace std;\nstruct node\n{\n    int l,r,lson,rson;\n    long long lmax,rmax,sum;\n    node()\n    {\n        lmax=rmax=sum=0;\n    }\n}a[3000010];\nlong long cnt,root[100010];\nvoid pushup(long long x)\n{\n    a[x].sum=a[a[x].lson].sum+a[a[x].rson].sum;\n    a[x].lmax=max(a[a[x].lson].lmax,a[a[x].lson].sum+a[a[x].rson].lmax);\n    a[x].rmax=max(a[a[x].rson].rmax,a[a[x].lson].rmax+a[a[x].rson].sum);\n}\nvoid pushup(node &x,node l,node r)\n{\n    x.lmax=max(l.lmax,l.sum+r.lmax);\n    x.rmax=max(r.rmax,l.rmax+r.sum);\n    x.sum=l.sum+r.sum;\n}\nlong long build(long long l,long long r)\n{\n    long long x=++cnt;\n    a[x].l=l;\n    a[x].r=r;\n    if(l==r)\n    {\n        a[x].lmax=a[x].rmax=a[x].sum=1;\n        return x;\n    }\n    long long mid=(l+r)>>1;\n    a[x].lson=build(l,mid);\n    a[x].rson=build(mid+1,r);\n    pushup(x);\n    return x;\n}\nlong long update(long long x,long long p,long long v)\n{\n    if(a[x].l>p||a[x].r<p)\n    {\n        return x;\n    }\n    long long now=++cnt;\n    a[now]=a[x];\n    if(a[x].l==a[x].r)\n    {\n        a[now].sum=a[now].lmax=a[now].rmax=v;\n        return now;\n    }\n    a[now].lson=update(a[x].lson,p,v);\n    a[now].rson=update(a[x].rson,p,v);\n    pushup(now);\n    return now;\n}\nnode query(long long x,long long l,long long r)\n{\n    if(l<=a[x].l&&a[x].r<=r)\n    {\n        return a[x];\n    }\n    long long mid=(a[x].l+a[x].r)>>1;\n    if(l<=mid&&mid<r)\n    {\n        node ans;\n        pushup(ans,query(a[x].lson,l,r),query(a[x].rson,l,r));\n        return ans;\n    }\n    else if(l<=mid)\n    {\n        return query(a[x].lson,l,r);\n    }\n    else\n    {\n        return query(a[x].rson,l,r);\n    }\n}\nlong long q[101],b[100010],id[100010];\nbool check(long long mid)\n{\n    int val=0;\n    if(q[1]+1<=q[2]-1)\n    {\n        val+=query(root[mid],q[1]+1,q[2]-1).sum;\n    }\n    val+=query(root[mid],q[0],q[1]).rmax;\n    val+=query(root[mid],q[2],q[3]).lmax;\n    return val>=0;\n}\nbool cmp(long long x,long long y)\n{\n    return b[x]<b[y];\n}\nint main()\n{\n    long long n;\n    scanf(\"%lld\",&n);\n    root[1]=build(1,n);\n    for(long long i=1;i<=n;i++)\n    {\n        scanf(\"%lld\",&b[i]);\n        id[i]=i;\n    }\n    sort(id+1,id+1+n,cmp);\n    for(long long i=2;i<=n;i++)\n    {\n        root[i]=update(root[i-1],id[i-1],-1);\n    }\n    long long Q,ans=0;\n    scanf(\"%lld\",&Q);\n    while(Q--)\n    {\n        for(long long i=0;i<4;i++)\n        {\n            scanf(\"%lld\",&q[i]);\n            q[i]=(q[i]+ans)%n+1;\n        }\n        sort(q,q+4);\n        long long l=1,r=n;\n        while(l<=r)\n        {\n            long long mid=(l+r)>>1;\n            if(check(mid))\n            {\n                ans=b[id[mid]];\n                l=mid+1;\n            }\n            else\n            {\n                r=mid-1;\n            }\n        }\n        printf(\"%lld\\n\",ans);\n    }\n    return 0;\n}", "_detail_requested": true, "_cached_at": "2026-06-05 16:05:41"}