{"time": 34, "memory": 752, "problem": {"pid": "P4170", "title": "[CQOI2007] 涂色", "difficulty": 5, "type": "P"}, "sourceCodeLength": 582, "submitTime": 1747235766, "language": 27, "user": {"uid": 768551, "name": "lfh2024", "avatar": "https://cdn.luogu.com.cn/upload/usericon/768551.png", "slogan": "这个家伙很勤快，什么都留下了...", "isAdmin": false, "isBanned": false, "color": "Red", "ccfLevel": 7, "xcpcLevel": 0, "background": "https://cdn.luogu.com.cn/upload/image_hosting/dqbnruu6.png"}, "id": 217179301, "status": 12, "enableO2": true, "score": 100, "detail": {"compileResult": {"success": true, "opt2": false}, "judgeResult": {"finishedCaseCount": 10, "status": 0, "time": 0, "memory": 0, "score": 0}, "version": 400}, "sourceCode": "#include<bits/stdc++.h>\nusing namespace std;\nchar s[101];\nint dp[101][101];\nint main()\n{\n    scanf(\"%s\",s+1);\n    int n=strlen(s+1);\n    memset(dp,0x3f,sizeof(dp));\n    for(int i=1;i<=n;i++)\n    {\n        dp[i][i]=1;\n    }\n    for(int len=2;len<=n;len++)\n    {\n        for(int l=1,r=len;r<=n;l++,r++)\n        {\n            if(s[l]==s[r])\n            {\n                dp[l][r]=dp[l][r-1];\n            }\n            for(int k=l;k<r;k++)\n            {\n                dp[l][r]=min(dp[l][r],dp[l][k]+dp[k+1][r]);\n            }\n        }\n    }\n    printf(\"%d\",dp[1][n]);\n    return 0;\n}", "_detail_requested": true, "_cached_at": "2026-06-05 17:04:34"}