{"time": 465, "memory": 10468, "problem": {"pid": "P4290", "title": "[HAOI2008] 玩具取名", "difficulty": 4, "type": "P"}, "sourceCodeLength": 1649, "submitTime": 1747667355, "language": 27, "user": {"uid": 768551, "name": "lfh2024", "avatar": "https://cdn.luogu.com.cn/upload/usericon/768551.png", "slogan": "这个家伙很勤快，什么都留下了...", "isAdmin": false, "isBanned": false, "color": "Red", "ccfLevel": 7, "xcpcLevel": 0, "background": "https://cdn.luogu.com.cn/upload/image_hosting/dqbnruu6.png"}, "id": 217818075, "status": 12, "enableO2": true, "score": 100, "detail": {"compileResult": {"success": true, "opt2": false}, "judgeResult": {"finishedCaseCount": 10, "status": 0, "time": 0, "memory": 0, "score": 0}, "version": 400}, "sourceCode": "#include<bits/stdc++.h>\nusing namespace std;\nbool flag[210][210][210],dp[210][210][210];\nmap<char,int> id;\nchar s[210];\nint main()\n{\n    id['W']=1;\n    id['I']=2;\n    id['N']=3;\n    id['G']=4;\n    int w,I,n,g;\n    scanf(\"%d%d%d%d\",&w,&I,&n,&g);\n    for(int i=1;i<=w;i++)\n    {\n        char a,b;\n        cin>>a>>b;\n        flag[1][id[a]][id[b]]=1;\n    }\n    for(int i=1;i<=I;i++)\n    {\n        char a,b;\n        cin>>a>>b;\n        flag[2][id[a]][id[b]]=1;\n    }\n    for(int i=1;i<=n;i++)\n    {\n        char a,b;\n        cin>>a>>b;\n        flag[3][id[a]][id[b]]=1;\n    }\n    for(int i=1;i<=g;i++)\n    {\n        char a,b;\n        cin>>a>>b;\n        flag[4][id[a]][id[b]]=1;\n    }\n    scanf(\"%s\",s+1);\n    int m=strlen(s+1);\n    for(int i=1;i<=m;i++)\n    {\n        dp[i][i][id[s[i]]]=1;\n    }\n    for(int len=2;len<=m;len++)\n    {\n        for(int l=1,r=len;r<=m;l++,r++)\n        {\n            for(int k=l;k<r;k++)\n            {\n                for(int a=1;a<=4;a++)\n                {\n                    for(int b=1;b<=4;b++)\n                    {\n                        for(int c=1;c<=4;c++)\n                        {\n                            dp[l][r][a]|=flag[a][b][c]&dp[l][k][b]&dp[k+1][r][c];\n                        }\n                    }\n                }\n            }\n        }\n    }\n    int f=0;\n    if(dp[1][m][1])\n    {\n        printf(\"W\");\n        f=1;\n    }\n    if(dp[1][m][2])\n    {\n        printf(\"I\");\n        f=1;\n    }\n    if(dp[1][m][3])\n    {\n        printf(\"N\");\n        f=1;\n    }\n    if(dp[1][m][4])\n    {\n        printf(\"G\");\n        f=1;\n    }\n    if(f==0)\n    {\n        printf(\"The name is wrong!\");\n    }\n    return 0;\n}", "_detail_requested": true, "_cached_at": "2026-06-05 17:29:54"}