{"time": 73, "memory": 680, "problem": {"pid": "P11229", "title": "[CSP-J 2024] 小木棍", "difficulty": 3, "type": "P"}, "sourceCodeLength": 672, "submitTime": 1753607855, "language": 28, "user": {"uid": 960557, "name": "Chen_Junan", "avatar": "https://cdn.luogu.com.cn/upload/usericon/960557.png", "slogan": "做一道难题，总比刷一百道水题来的方便；做一百道难题，总比刷一道水题来得有趣。", "isAdmin": false, "isBanned": false, "color": "Green", "ccfLevel": 0, "xcpcLevel": 0, "background": "https://cdn.luogu.com.cn/upload/image_hosting/udwgp8oh.png"}, "id": 227214823, "status": 12, "enableO2": true, "score": 100, "detail": {"compileResult": {"success": true, "opt2": false}, "judgeResult": {"finishedCaseCount": 10, "status": 0, "time": 0, "memory": 0, "score": 0}, "version": 400}, "sourceCode": "#include<bits/stdc++.h>\nusing namespace std;\n#define int long long\nconst int maxn=25;\nint t,n,f[maxn],a[]= {6,2,5,5,4,5,6,3,7,6};\nsigned main() {\n\tios::sync_with_stdio(0),cin.tie(0),cout.tie(0);\n\tcin>>t;\n\tfill(f+1,f+maxn,INT_MAX);\n\tfor(int i=1; i<10; i++) {\n\t\tif(f[a[i]]>i) {\n\t\t\tf[a[i]]=i;\n\t\t}\n\t}\n\tfor(int i=2; i<maxn; i++) {\n\t\tfor(int j=0; j<10; j++) {\n\t\t\tif(i+a[j]<maxn&&f[i+a[j]]>(10*f[i]+j)) {\n\t\t\t\tf[i+a[j]]=10*f[i]+j;\n\t\t\t}\n\t\t}\n\t}\n\twhile(t--) {\n\t\tcin>>n;\n\t\tif(n==1) {\n\t\t\tcout<<-1<<\"\\n\";\n\t\t} else if(n<maxn) {\n\t\t\tcout<<f[n]<<\"\\n\";\n\t\t} else {\n\t\t\tint c=(n-(maxn-1)+6)/7;\n\t\t\tcout<<f[n-c*7];\n\t\t\tfor(int i=1; i<=c; i++) {\n\t\t\t\tcout<<8;\n\t\t\t}\n\t\t\tcout<<\"\\n\";\n\t\t}\n\t}\n\treturn 0;\n}", "_detail_requested": true, "_cached_at": "2026-06-05 13:03:12"}