{"time": 57, "memory": 680, "problem": {"pid": "P1238", "title": "走迷宫", "difficulty": 3, "type": "P"}, "sourceCodeLength": 1924, "submitTime": 1737254632, "language": 28, "user": {"uid": 960557, "name": "Chen_Junan", "avatar": "https://cdn.luogu.com.cn/upload/usericon/960557.png", "slogan": "做一道难题，总比刷一百道水题来的方便；做一百道难题，总比刷一道水题来得有趣。", "isAdmin": false, "isBanned": false, "color": "Green", "ccfLevel": 0, "xcpcLevel": 0, "background": "https://cdn.luogu.com.cn/upload/image_hosting/udwgp8oh.png"}, "id": 199138659, "status": 14, "enableO2": true, "score": 10, "detail": {"compileResult": {"success": true, "opt2": false}, "judgeResult": {"finishedCaseCount": 20, "status": 0, "time": 0, "memory": 0, "score": 0}, "version": 400}, "sourceCode": "#include <iostream>\r\n#include <vector>\r\n#include <string>\r\nusing namespace std;\r\n\r\n// 定义方向数组：上、左、下、右\r\nconst int dx[] = {-1, 0, 1, 0};\r\nconst int dy[] = {0, -1, 0, 1};\r\n\r\n// DFS函数\r\nbool dfs(vector<vector<int>>& maze, vector<vector<bool>>& visited, vector<pair<int, int>>& path, pair<int, int> start, pair<int, int> end) {\r\n    int x = start.first, y = start.second;\r\n\r\n    // 如果当前点是终点，输出路径\r\n    if (start == end) {\r\n        for (size_t i = 0; i < path.size(); ++i) {\r\n            if (i != 0) cout << \" -> \";\r\n            cout << \"(\" << path[i].first << \",\" << path[i].second << \")\";\r\n        }\r\n        cout << endl;\r\n        return true;\r\n    }\r\n\r\n    // 标记当前点为已访问\r\n    visited[x][y] = true;\r\n\r\n    bool found = false;\r\n    for (int i = 0; i < 4; ++i) { // 遍历四个方向\r\n        int nx = x + dx[i], ny = y + dy[i];\r\n        // 检查下一个点是否在迷宫范围内、是否可走、是否未访问\r\n        if (nx >= 0 && nx < maze.size() && ny >= 0 && ny < maze[0].size() && maze[nx][ny] == 1 && !visited[nx][ny]) {\r\n            path.push_back({nx, ny}); // 将下一个点加入路径\r\n            if (dfs(maze, visited, path, {nx, ny}, end)) {\r\n                found = true;\r\n            }\r\n            path.pop_back(); // 回溯，移除最后一个点\r\n        }\r\n    }\r\n\r\n    // 回溯，标记当前点为未访问\r\n    visited[x][y] = false;\r\n    return found;\r\n}\r\n\r\n// 主函数\r\nint main() {\r\n    int m, n;\r\n    cin >> m >> n;\r\n\r\n    // 读取迷宫\r\n    vector<vector<int>> maze(m, vector<int>(n));\r\n    for (int i = 0; i < m; ++i) {\r\n        for (int j = 0; j < n; ++j) {\r\n            cin >> maze[i][j];\r\n        }\r\n    }\r\n\r\n    // 读取起始点和结束点\r\n    pair<int, int> start, end;\r\n    cin >> start.first >> start.second;\r\n    cin >> end.first >> end.second;\r\n\r\n    // 初始化访问标记数组和路径\r\n    vector<vector<bool>> visited(m, vector<bool>(n, false));\r\n    vector<pair<int, int>> path;\r\n    path.push_back(start);\r\n\r\n    // 调用DFS函数\r\n    if (!dfs(maze, visited, path, start, end)) {\r\n        cout << -1 << endl; // 如果没有找到路径，输出-1\r\n    }\r\n\r\n    return 0;\r\n}", "_detail_requested": true, "_cached_at": "2026-06-05 13:02:46"}