{"time": 643, "memory": 1488, "problem": {"pid": "P5661", "title": "[CSP-J 2019] 公交换乘", "difficulty": 2, "type": "P"}, "sourceCodeLength": 536, "submitTime": 1721784236, "language": 4, "user": {"uid": 960557, "name": "Chen_Junan", "avatar": "https://cdn.luogu.com.cn/upload/usericon/960557.png", "slogan": "做一道难题，总比刷一百道水题来的方便；做一百道难题，总比刷一道水题来得有趣。", "isAdmin": false, "isBanned": false, "color": "Green", "ccfLevel": 0, "xcpcLevel": 0, "background": "https://cdn.luogu.com.cn/upload/image_hosting/udwgp8oh.png"}, "id": 168142532, "status": 12, "enableO2": true, "score": 100, "detail": {"compileResult": {"success": true, "opt2": false}, "judgeResult": {"finishedCaseCount": 20, "status": 0, "time": 0, "memory": 0, "score": 0}, "version": 400}, "sourceCode": "#include<bits/stdc++.h>\r\nusing namespace std;\r\nint o,n,t[100001],p[100001],ans,top,m=1,yh[100001],sj[100001],k;\r\nbool r[100001];\r\nint main() {\r\n\tcin>>n;\r\n\tfor(int i=1; i<=n; i++) {\r\n\t\tcin>>o>>p[i]>>t[i];\r\n\t\tif(o==0) yh[++top]=p[i],sj[top]=t[i],ans+=p[i];\r\n\t\telse {\r\n\t\t\tk=0;\r\n\t\t\tfor(int j=m; j<=top; j++) {\r\n\t\t\t\t\tif(r[j]) {\r\n\t\t\t\t\t\tcontinue;\r\n\t\t\t\t\t}\r\n\t\t\t\t\tif(t[i]-sj[j]>45) {\r\n\t\t\t\t\t\tm=j;\r\n\t\t\t\t\t} else if(yh[j]>=p[i]) {\r\n\t\t\t\t\t\tk=j;\r\n\t\t\t\t\t\tr[k]=true;\r\n\t\t\t\t\t\tbreak;\r\n\t\t\t\t\t}\r\n\t\t\t\t}\r\n\t\t\t\tif(!k) ans+=p[i];\r\n\t\t\t}\r\n\t}\r\n\tcout<<ans;\r\n\treturn 0;\r\n}", "_detail_requested": true, "_cached_at": "2026-06-05 13:07:10"}