{"time": 502, "memory": 15712, "problem": {"pid": "P1937", "title": "[USACO10MAR] Barn Allocation G", "difficulty": 5, "type": "P"}, "sourceCodeLength": 1789, "submitTime": 1770345473, "language": 12, "user": {"uid": 1791119, "name": "Zrokee", "avatar": "https://cdn.luogu.com.cn/upload/usericon/1791119.png", "slogan": "菜就多练", "isAdmin": false, "isBanned": false, "color": "Orange", "ccfLevel": 0, "xcpcLevel": 0, "background": "https://cdn.luogu.com.cn/upload/image_hosting/84v1y4kd.png"}, "id": 261288636, "status": 12, "enableO2": true, "score": 100, "detail": {"compileResult": {"success": true, "opt2": false}, "judgeResult": {"finishedCaseCount": 12, "status": 0, "time": 0, "memory": 0, "score": 0}, "version": 400}, "sourceCode": "#include <bits/stdc++.h>\n#define int long long\nusing namespace std;\nstruct Edge {\n\tint L , R , lz , Min;\n};\nEdge tr[1000005];\npair < int , int > Cow[1000005];\nint n , m , C[1000005];\nint ans;\nbool cmp( pair < int , int > a , pair < int , int > b ) {\n\tif( a.second != b.second ) {\n\t\treturn a.second < b.second;\n\t}\n\treturn a.first < b.first;\n}\nvoid build( int p , int L , int R ) {\n\ttr[p] = { L , R , 0 , ( int )1e9 };\n\tif( L == R ) {\n\t\ttr[p].Min = C[L];\n\t\treturn;\n\t}\n\tint mid = ( L + R ) / 2;\n\tbuild( p << 1 , L , mid );\n\tbuild( p << 1 | 1 , mid + 1 , R );\n\ttr[p].Min = min( tr[p << 1].Min , tr[p << 1 | 1].Min );\n}\nvoid uplz( int p , int lz ) {\n\ttr[p].lz += lz;\n\ttr[p].Min -= lz;\n}\nvoid pushdown( int p ) {\n\tif( tr[p].lz ) {\n\t\tuplz( p << 1 , tr[p].lz );\n\t\tuplz( ( p << 1 ) + 1 , tr[p].lz );\n\t\ttr[p].lz = 0;\n\t}\n}\nvoid modify( int p , int l , int r ) {\n\tif( tr[p].L > r || tr[p].R < l ) {\n\t\treturn;\n\t}\n\tif( tr[p].L >= l && tr[p].R <= r ) {\n\t\tuplz( p , 1 );\n\t\treturn;\n\t}\n\tpushdown( p );\n\tmodify( p << 1 , l , r );\n\tmodify( ( p << 1 ) + 1 , l , r );\n\ttr[p].Min = min( tr[p << 1].Min , tr[( p << 1 ) + 1].Min );\n}\nint query( int p , int a , int b ) {\n\tif( tr[p].L > b || tr[p].R < a ) {\n\t\treturn ( int )1e18;\n\t}\n\tif( tr[p].L >= a && tr[p].R <= b ) {\n\t\treturn tr[p].Min;\n\t}\n\tint sum = 0;\n\tpushdown( p );\n\tsum = min( query( p << 1 , a , b ) , query( ( p << 1 ) + 1 , a , b ) );\n\treturn sum;\n}\nsigned main() {\n\tcin >> n >> m;\n\tfor( int i = 1 ; i <= n ; i++ ) {\n\t\tcin >> C[i];\n\t}\n\tbuild( 1 , 1 , n );\n\tfor( int i = 1 ; i <= m ; i++ ) {\n\t\tcin >> Cow[i].first >> Cow[i].second;\n\t}\n\tsort( Cow + 1 , Cow + m + 1 , cmp );\n\tfor( int i = 1 ; i <= m ; i++ ) {\n\t\tif( query( 1 , Cow[i].first , Cow[i].second ) > 0 ) {\n\t\t\tans++;\n\t\t\tmodify( 1 , Cow[i].first , Cow[i].second );\n\t\t}\n\t}\n\tcout << ans;\n\treturn 0;\n}", "_detail_requested": true, "_cached_at": "2026-06-05 11:20:00"}