{"time": 175, "memory": 1096, "problem": {"pid": "P4265", "title": "[USACO18FEB] Snow Boots S", "difficulty": 4, "type": "P"}, "sourceCodeLength": 701, "submitTime": 1777643645, "language": 4, "user": {"uid": 1791119, "name": "Zrokee", "avatar": "https://cdn.luogu.com.cn/upload/usericon/1791119.png", "slogan": "菜就多练", "isAdmin": false, "isBanned": false, "color": "Orange", "ccfLevel": 0, "xcpcLevel": 0, "background": "https://cdn.luogu.com.cn/upload/image_hosting/84v1y4kd.png"}, "id": 276245496, "status": 12, "enableO2": true, "score": 100, "detail": {"compileResult": {"success": true, "opt2": false}, "judgeResult": {"finishedCaseCount": 10, "status": 0, "time": 0, "memory": 0, "score": 0}, "version": 400}, "sourceCode": "#include <bits/stdc++.h>\n#define int long long\nusing namespace std;\nconst int N = 255;\nint n, b;\nint dp[N][N];\nint f[N];\nint s[N];\nint d[N];\nsigned main() {\n\tcin >> n >> b;\n\tfor (int i = 1; i <= n; i++) {\n\t\tcin >> f[i];\n\t}\n\tfor (int i = 1; i <= b; i++) {\n\t\tcin >> s[i] >> d[i];\n\t}\n\tdp[1][1] = 1;\n\tfor (int i = 1; i <= n; i++) {\n\t\tfor (int j = 1; j <= b; j++) {\n\t\t\tif (dp[i][j]) {\n\t\t\t\tfor (int k = j; k <= b; k++) {\n\t\t\t\t\tif (f[i] <= s[k]) {\n\t\t\t\t\t\tfor (int l = i + 1; l <= min (n, i + d[k]); l++) {\n\t\t\t\t\t\t\tif (f[l] <= s[k]) {\n\t\t\t\t\t\t\t\tdp[l][k] = 1;\n\t\t\t\t\t\t\t}\n\t\t\t\t\t\t}\n\t\t\t\t\t}\n\t\t\t\t}\n\t\t\t}\n\t\t}\n\t}\n    for (int i = 1; i <= b; i++) {\n    \tif (dp[n][i]) {\n    \t\tcout << i - 1;\n    \t\treturn 0;\n\t\t}\n\t}\n\treturn 0;\n} ", "_detail_requested": true, "_cached_at": "2026-06-05 11:25:00"}