{"time": 268, "memory": 17212, "problem": {"pid": "P7167", "title": "[eJOI 2020] Fountain (Day1)", "difficulty": 4, "type": "P"}, "sourceCodeLength": 1165, "submitTime": 1780062178, "language": 34, "user": {"uid": 1791119, "name": "Zrokee", "avatar": "https://cdn.luogu.com.cn/upload/usericon/1791119.png", "slogan": "菜就多练", "isAdmin": false, "isBanned": false, "color": "Orange", "ccfLevel": 0, "xcpcLevel": 0, "background": "https://cdn.luogu.com.cn/upload/image_hosting/84v1y4kd.png"}, "id": 279822776, "status": 12, "enableO2": true, "score": 100, "detail": {"compileResult": {"success": true, "opt2": false}, "judgeResult": {"finishedCaseCount": 16, "status": 0, "time": 0, "memory": 0, "score": 0}, "version": 400}, "sourceCode": "#include<bits/stdc++.h>\n#define ll long long\n#define ri register int\nusing namespace std;\nconst int MAXN=1e5+10;\nint n,q,d[MAXN],c[MAXN],r,v,b[MAXN],nxt[MAXN][20],sum[MAXN][20];\nstack <int> stk;\nvoid find_max () {\n\tfor (ri i = 1; i <= n; i++) {\n\t\twhile (stk.size () && d[i] > d[stk.top ()]) {\n\t\t\tnxt[stk.top ()][0] = i;\n\t\t\tsum[stk.top ()][0] = c[i];\n\t\t\tstk.pop ();\n\t\t}\n\t\tstk.push (i);\n\t}\n\twhile (stk.size ()) {\n\t\tnxt[stk.top ()][0] = 0;\n\t\tstk.pop ();\n\t}\n\treturn ;\n}\nvoid pre_rmq () {\n\tfor (ri j = 1; (1 << j) <= n; j++) {\n\t\tfor (ri i = 1; i + (1 << j) <= n; i++) {\n\t\t\tnxt[i][j] = nxt[nxt[i][j - 1]][j - 1];\n\t\t\tsum[i][j] = sum[i][j - 1] + sum[nxt[i][j - 1]][j - 1];\n\t\t}\n\t}\n\treturn ;\n}\nint query (int r, int val) {\n\tif (c[r] >= val) {\n\t\treturn r;\n\t}\n\tval -= c[r];\n\tfor (ri i = 18; i >= 0; i--) {\n\t\tif (nxt[r][i] != 0 && val > sum[r][i]) {\n\t\t\tval -= sum[r][i];\n\t\t\tr = nxt[r][i];\n\t\t}\n\t}\n\treturn nxt[r][0];\n}\nint main() {\n\tcin >> n >> q;\n    for (ri i = 1; i <= n; i++) {\n        cin >> d[i] >> c[i];\n    }\n\tmemset (sum, 0x3f, sizeof (sum));\n\tfind_max ();\n\tpre_rmq ();\n\tfor (ri i = 1; i <= q; i++) {\n\t\tcin >> r >> v;\n        cout << query (r, v) << '\\n';\n\t}\n\treturn 0;\n}", "_detail_requested": true, "_cached_at": "2026-06-05 11:22:15"}