{"time": 274, "memory": 6720, "problem": {"pid": "P10940", "title": "舞动的夜晚", "difficulty": 6, "type": "P"}, "sourceCodeLength": 2223, "submitTime": 1771916215, "language": 28, "user": {"uid": 907368, "name": "andycode", "avatar": "https://cdn.luogu.com.cn/upload/usericon/907368.png", "slogan": "Always continue, never break || 天灵灵，地灵灵，代码一定行 || 逸一时，误一世，逸久逸久罢以零 || 服役 OIer", "isAdmin": false, "isBanned": false, "color": "Orange", "ccfLevel": 7, "xcpcLevel": 0, "background": "https://cdn.luogu.com.cn/upload/image_hosting/sob0rftg.png"}, "id": 263767410, "status": 12, "enableO2": true, "score": 100, "detail": {"compileResult": {"success": true, "opt2": false}, "judgeResult": {"finishedCaseCount": 10, "status": 0, "time": 0, "memory": 0, "score": 0}, "version": 400}, "sourceCode": "#include <bits/stdc++.h>\nusing namespace std;\n\nconst int N=2e4+10,M=2e5+N*2,INF=1e8;\n\nint n,m,t;\nint head[N],ver[M],edge[M],nxt[M],tot=1;\nint S,T,d[N],now[N],q[N];\nint dfn[N],low[N],num,stk[N],top,c[N],cnt;\nbool ins[N];\nvector<int> e[N],ans;\n\nvoid add(int x,int y){\n    ver[++tot]=y,edge[tot]=1,nxt[tot]=head[x],head[x]=tot;\n    ver[++tot]=x,edge[tot]=0,nxt[tot]=head[y],head[y]=tot;\n}\n\nbool bfs(){\n    memset(d,0,sizeof(d));\n    d[S]=1,now[S]=head[S];\n    int hh=1,tt=0;\n    q[++tt]=S;\n    while(hh<=tt){\n        int x=q[hh++];\n        for(int i=head[x],y;i;i=nxt[i])\n            if(edge[i] && !d[y=ver[i]]){\n                d[y]=d[x]+1,now[y]=head[y];\n                if(y==T)\n                    return true;\n                q[++tt]=y;\n            }\n    }\n    return false;\n}\n\nint Dinic(int x,int flow){\n    if(x==T)\n        return flow;\n    int res=0;\n    for(int i=now[x],y;i && res<flow;i=nxt[i]){\n        y=ver[i],now[x]=i;\n        if(d[y]==d[x]+1 && edge[i]){\n            int tmp=Dinic(y,min(flow-res,edge[i]));\n            if(!tmp) d[y]=0;\n            edge[i]-=tmp,edge[i^1]+=tmp;\n            res+=tmp;\n        }\n    }\n    return res;\n}\n\nvoid tarjan(int x){\n    dfn[x]=low[x]=++num;\n    stk[++top]=x,ins[x]=1;\n    for(int y:e[x])\n        if(!dfn[y]){\n            tarjan(y);\n            low[x]=min(low[x],low[y]);\n        }else if(ins[y])\n            low[x]=min(low[x],dfn[y]);\n    if(dfn[x]==low[x]){\n        cnt++;\n        int z;\n        do{\n            z=stk[top--],c[z]=cnt,ins[z]=0;\n        }while(z!=x);\n    }\n}\n\nint main(){\n    //freopen(\"main.in\",\"r\",stdin);\n    scanf(\"%d%d%d\",&n,&m,&t);\n    for(int i=1;i<=t;i++){\n        int a,b;\n        scanf(\"%d%d\",&a,&b);\n        add(a,n+b);\n    }\n    S=n+m+1,T=n+m+2;\n    for(int i=1;i<=n;i++)\n        add(S,i);\n    for(int i=1;i<=m;i++)\n        add(n+i,T);\n    while(bfs())\n        while(Dinic(S,INF));\n    for(int i=2;i<=tot;i++)\n        if(edge[i])\n            e[ver[i^1]].push_back(ver[i]);\n    for(int i=1;i<=n+m+2;i++)\n        if(!dfn[i])\n            tarjan(i);\n    for(int i=1;i<=t;i++)\n        if(edge[i*2] && c[ver[i*2]]!=c[ver[i*2+1]])\n            ans.push_back(i);\n    printf(\"%d\\n\",ans.size());\n    for(int i:ans)\n        printf(\"%d \",i);\n    return 0;\n}", "_detail_requested": true, "_cached_at": "2026-06-05 19:49:09"}