{"time": 236, "memory": 35400, "problem": {"pid": "P2868", "title": "[USACO07DEC] Sightseeing Cows G", "difficulty": 5, "type": "P"}, "sourceCodeLength": 1377, "submitTime": 1780558638, "language": 28, "user": {"uid": 907368, "name": "andycode", "avatar": "https://cdn.luogu.com.cn/upload/usericon/907368.png", "slogan": "Always continue, never break || 天灵灵，地灵灵，代码一定行 || 逸一时，误一世，逸久逸久罢以零 || 服役 OIer", "isAdmin": false, "isBanned": false, "color": "Orange", "ccfLevel": 7, "xcpcLevel": 0, "background": "https://cdn.luogu.com.cn/upload/image_hosting/sob0rftg.png"}, "id": 280597215, "status": 12, "enableO2": true, "score": 100, "detail": {"compileResult": {"success": true, "opt2": false}, "judgeResult": {"finishedCaseCount": 11, "status": 0, "time": 0, "memory": 0, "score": 0}, "version": 400}, "sourceCode": "#include <bits/stdc++.h>\nusing namespace std;\n\nconst int N=1e6;\nconst double eps=1e-7;\n\nstruct Edge{\n    int u,v,w;\n}edge[N*5];\n\nstruct Node{\n    int to;\n    double val;\n};\n\nint n,m,f[N],cnt[N],q[N],hh,tt;\ndouble dis[N];\nbool inq[N];\nvector<Node> e[N];\n\nbool check(double mid){\n    for(int i=1;i<=n+1;i++) e[i].clear(),cnt[i]=0,inq[i]=0;\n    for(int i=1;i<=m;i++){\n        int u=edge[i].u,v=edge[i].v,w=edge[i].w;\n        e[u].push_back({v,mid*w-f[v]});\n    }\n    for(int i=1;i<=n;i++) e[n+1].push_back({i,0});\n    for(int i=1;i<=n+1;i++) dis[i]=1e18;\n    dis[n+1]=0;\n    hh=1,tt=0;\n    q[++tt]=n+1;\n    inq[n+1]=1;\n    while(hh<=tt){\n        int x=q[hh++];\n        inq[x]=0;\n        for(Node y:e[x])\n            if(dis[y.to]>dis[x]+y.val){\n                dis[y.to]=dis[x]+y.val;\n                cnt[y.to]++;\n                if(cnt[y.to]>n+2) return true;\n                if(!inq[y.to]){\n                    q[++tt]=y.to;\n                    inq[y.to]=1;\n                }\n            }\n    }\n    return false;\n}\n\nint main(){\n    scanf(\"%d%d\",&n,&m);\n    for(int i=1;i<=n;i++)\n        scanf(\"%d\",&f[i]);\n    for(int i=1;i<=m;i++)\n        scanf(\"%d%d%d\",&edge[i].u,&edge[i].v,&edge[i].w);\n    double l=0,r=1e6;\n    while(l+eps<r){\n        double mid=(l+r)/2;\n        if(check(mid))\n            l=mid;\n        else\n            r=mid;\n    }\n    printf(\"%.2lf\",l);\n    return 0;\n}", "_detail_requested": true, "_cached_at": "2026-06-05 19:54:26"}