{"time": 456, "memory": 315284, "problem": {"pid": "P6715", "title": "[CCO 2018] Fun Palace", "difficulty": 7, "type": "P"}, "sourceCodeLength": 1077, "submitTime": 1760602394, "language": 28, "user": {"uid": 907368, "name": "andycode", "avatar": "https://cdn.luogu.com.cn/upload/usericon/907368.png", "slogan": "Always continue, never break || 天灵灵，地灵灵，代码一定行 || 逸一时，误一世，逸久逸久罢以零 || 服役 OIer", "isAdmin": false, "isBanned": false, "color": "Orange", "ccfLevel": 7, "xcpcLevel": 0, "background": "https://cdn.luogu.com.cn/upload/image_hosting/sob0rftg.png"}, "id": 240857354, "status": 12, "enableO2": true, "score": 100, "detail": {"compileResult": {"success": true, "opt2": false}, "judgeResult": {"finishedCaseCount": 21, "status": 0, "time": 0, "memory": 0, "score": 0}, "version": 400}, "sourceCode": "#include <bits/stdc++.h>\nusing namespace std;\n\nconst int N=2010,M=4e4+10;\n\nint n,m,a[N],b[N],f[N][M];\n\nint main(){\n    int c,T=1;\n    while(T--){\n        scanf(\"%d%d\",&n,&m);\n        for(int i=1;i<n;i++)\n            scanf(\"%d%d\",&a[i],&b[i]);\n        memset(f,0xcf,sizeof(f));\n        for(int j=0;j<m;j++)\n            f[1][j]=j;\n        for(int i=1;i<n;i++){\n            int tmp=-1e9;\n            for(int j=0;j<a[i];j++)\n                tmp=max(tmp,f[i][j]);\n            for(int j=0;j<=4e4;j++){\n                if(j>=a[i]+b[i])\n                    f[i+1][j]=max(f[i+1][j],f[i][j]);\n                else if(j>=a[i])\n                    f[i+1][j-a[i]]=max(f[i+1][j-a[i]],f[i][j]);\n                else{\n                    f[i+1][j+b[i]]=max(f[i+1][j+b[i]],f[i][j]+b[i]);\n                    tmp=max(tmp,f[i][j]);\n                }\n            }\n            for(int j=0;j<b[i];j++)\n                f[i+1][j]=max(f[i+1][j],tmp+j);\n        }\n        int ans=-1e9;\n        for(int i=0;i<=4e4;i++)\n            ans=max(ans,f[n][i]);\n        printf(\"%d\\n\",ans);\n    }\n    return 0;\n}\n", "_detail_requested": true, "_cached_at": "2026-06-05 19:39:05"}