{"time": 417, "memory": 221584, "problem": {"pid": "P9753", "title": "[CSP-S 2023] 消消乐", "difficulty": 5, "type": "P"}, "sourceCodeLength": 493, "submitTime": 1779106451, "language": 3, "user": {"uid": 907368, "name": "andycode", "avatar": "https://cdn.luogu.com.cn/upload/usericon/907368.png", "slogan": "Always continue, never break || 天灵灵，地灵灵，代码一定行 || 逸一时，误一世，逸久逸久罢以零 || 服役 OIer", "isAdmin": false, "isBanned": false, "color": "Orange", "ccfLevel": 7, "xcpcLevel": 0, "background": "https://cdn.luogu.com.cn/upload/image_hosting/sob0rftg.png"}, "id": 278460591, "status": 12, "enableO2": true, "score": 100, "detail": {"compileResult": {"success": true, "opt2": false}, "judgeResult": {"finishedCaseCount": 20, "status": 0, "time": 0, "memory": 0, "score": 0}, "version": 400}, "sourceCode": "#include <bits/stdc++.h>\nusing namespace std;\n\nconst int N=2e6+10;\n\nint n,p[N],f[N],lst[N][26];\nlong long ans;\nchar s[N];\n\nint main(){\n    scanf(\"%d\",&n);\n    scanf(\"%s\",s+1);\n    p[1]=-1;\n    lst[1][s[1]-'a']=1;\n    for(int i=2;i<=n;i++){\n        p[i]=lst[i-1][s[i]-'a']-1;\n        if(~p[i])\n            for(int j=0;j<26;j++)\n                lst[i][j]=lst[p[i]][j];\n        lst[i][s[i]-'a']=i;\n        if(~p[i]) f[i]=f[p[i]]+1;\n        ans+=f[i];\n    }\n    printf(\"%lld\",ans);\n    return 0;\n}", "_detail_requested": true, "_cached_at": "2026-06-05 19:50:00"}